pfun_common/__init__.py
pfun_common/enums.py
pfun_common/plot.py
pfun_common/settings.py
pfun_common/utils.py
pfun_common-0.1.28.dist-info/METADATA
pfun_common-0.1.28.dist-info/WHEEL
pfun_common-0.1.28.dist-info/RECORD
