Metadata-Version: 2.4
Name: pfun-common
Version: 0.1.28
Summary: Common utilities and functions for PFun projects.
Author-email: Robbie Capps <robbie@pfun.me>
Requires-Python: ==3.12.11
Requires-Dist: matplotlib>=3.8.0
Requires-Dist: pandas>=2.2.0
Requires-Dist: pydantic-settings>=2.2.1
